{"workspace":{"version":"3.0.3","workspace":{"blocks":{"languageVersion":0,"blocks":[{"type":"procedures_defnoreturn","id":"kY65@m^WH1^^gypO8ZnJ","x":1209,"y":2261,"extraState":{"procedureId":"Ih5!k9+Fw?I6be,p}+@$"},"icons":{"comment":{"text":"Опишите эту функцию…","pinned":false,"height":80,"width":160}},"fields":{"NAME":"validate_bank_statement"},"inputs":{"STACK":{"block":{"type":"comment_block","id":"Jg5N*a`3dI,B9zEFiU0C","fields":{"TEXT":"Выполняет проверку структуры банковской выписки.\r\n\r\nПараметры:\r\n- statement — DataFrame с данными банковской выписки\r\n\r\nФункция:\r\n- проверяет наличие обязательных колонок в DataFrame;\r\n- завершает выполнение программы при отсутствии обязательных колонок;"},"next":{"block":{"type":"write_log","id":"NrxS.jdyOE:Q~h5H;g}I","fields":{"FIELDVALUE1":"info"},"inputs":{"VALUE1":{"shadow":{"type":"text","id":"BqDw)jzc:@Xw2D0F}-VB","fields":{"TEXT":""}},"block":{"type":"text","id":"mbGsTWFMb_%Bk~(gOmBJ","fields":{"TEXT":"Валидация банковской выписки..."}}}},"next":{"block":{"type":"group_block","id":"!v)h/4eo[]f5a5Cjfj|/","fields":{"FIELDVALUE":"Базовые пременные"},"inputs":{"DO":{"block":{"type":"variables_set","id":"dnZy8#x]o=i,}um5N$xZ","fields":{"VAR":{"id":"(W.XicDr)K8pasW5op.y"}},"inputs":{"VALUE":{"block":{"type":"lists_create_with","id":".17ULWGxJi?dB6[Soc:K","extraState":{"itemCount":6},"inputs":{"ADD0":{"block":{"type":"text","id":"Hkk_Ie$LI*$IS;x4cPM]","fields":{"TEXT":"Дата"}}},"ADD1":{"block":{"type":"text","id":"RWG$QvCD?7/`]{qx9U#7","fields":{"TEXT":"Сумма"}}},"ADD2":{"block":{"type":"text","id":"(ArH~dUo~{bo`uA/;QnJ","fields":{"TEXT":"Тип"}}},"ADD3":{"block":{"type":"text","id":"vAB5heK0T1N4`$(byHhV","fields":{"TEXT":"Назначение"}}},"ADD4":{"block":{"type":"text","id":"=UmIkdW;mZu^F?QQK_r]","fields":{"TEXT":"ИНН_контрагента"}}},"ADD5":{"block":{"type":"text","id":",@z$Hqs?-/B[vwn{|t7+","fields":{"TEXT":"Организация"}}}}}}},"next":{"block":{"type":"variables_set","id":"nnl`~rmf@3=tOGdsOw%m","icons":{"comment":{"text":"Присваивает переменной значение вставки","pinned":false,"height":74,"width":211,"bubbleRelLeft":-52.75,"bubbleRelTop":-98}},"fields":{"VAR":{"id":"%fM.Cf@lHUEcY$B#9+JD"}},"inputs":{"VALUE":{"block":{"type":"get_df_columns","id":"lu0DAr0,IG/ue,PWa]=:","inputs":{"VALUE1":{"block":{"type":"variables_get","id":"uWE2.E+j|4#7/s.x@PLU","fields":{"VAR":{"id":"%9v@:^Vx-]2?^Zi%Tcv}"}}}}}}}}}}}}},"next":{"block":{"type":"group_block","id":"X;00kkkx1BwF[GD)YDh5","fields":{"FIELDVALUE":"Проверка полей конфига"},"inputs":{"DO":{"block":{"type":"controls_forEach","id":"7!kuB$~T1N(pHoxaCuKg","fields":{"VAR":{"id":"MKoy}V;0qs@|B2tb1[4L"}},"inputs":{"LIST":{"block":{"type":"variables_get","id":"Ip5u6pEKy?gJ,^Bc!:uk","fields":{"VAR":{"id":"(W.XicDr)K8pasW5op.y"}}}},"DO":{"block":{"type":"controls_if","id":"S?PO(Fo%a5a;jL+/^Txw","inputs":{"IF0":{"block":{"type":"logic_compare","id":"xfPYNvy5ET5$1IC%#(mo","fields":{"OP":"EQ"},"inputs":{"A":{"block":{"type":"lists_indexOf","id":"v*KVPx^9iGr:/)hhq(c~","fields":{"END":"FIRST"},"inputs":{"VALUE":{"block":{"type":"variables_get","id":"!5nWxKxd*MeVb[oNaq}C","fields":{"VAR":{"id":"%fM.Cf@lHUEcY$B#9+JD"}}}},"FIND":{"block":{"type":"variables_get","id":":_i!U+1^M;?Op~*)$E,M","fields":{"VAR":{"id":"MKoy}V;0qs@|B2tb1[4L"}}}}}}},"B":{"block":{"type":"math_number","id":"yI[q+4==0@[DM(x9afdT","fields":{"NUM":-1}}}}}},"DO0":{"block":{"type":"write_log","id":"VpCX,yHWBcx@!YD@gWrN","fields":{"FIELDVALUE1":"error"},"inputs":{"VALUE1":{"shadow":{"type":"text","id":"n+8~IG[)#4_+=y*(To%`","fields":{"TEXT":""}},"block":{"type":"f_string","id":"5U}UTSj(sTy.Qj$|S0Yl","extraState":{},"fields":{"TEXT":"В банковской выпеске отсутсвует колонка: {column}"}}}},"next":{"block":{"type":"stop_robot","id":"V8fN/{WY)sy[(!Yx?FFN","inputs":{"VALUE1":{"shadow":{"type":"text","id":"+}/6+K`y9]?^KU.u4_`,","fields":{"TEXT":"Завершение работы робота"}}}}}}}}}}}},"next":{"block":{"type":"write_log","id":"E(1jMvS$G-z,%}Ge?|T2","fields":{"FIELDVALUE1":"info"},"inputs":{"VALUE1":{"shadow":{"type":"text","id":"(qth4J#/Tk^w_YtJuUJI","fields":{"TEXT":""}},"block":{"type":"text","id":"@IhYqSw%DY:]X4eg?;sF","fields":{"TEXT":"Все обязательные колонки в банковской выпеске существуют"}}}}}}}}}}}}}}}}}}},{"type":"procedures_defnoreturn","id":"S9*(aPY^T9zqDW!5S;MT","x":1214,"y":3108,"extraState":{"procedureId":"v?m+zr|}6[5e6`.}tvpe"},"icons":{"comment":{"text":"Опишите эту функцию…","pinned":false,"height":80,"width":160}},"fields":{"NAME":"validate_payment_row"},"inputs":{"STACK":{"block":{"type":"comment_block","id":"IBvm?dZByBk9a)tw,B`z","fields":{"TEXT":"Выполняет валидацию данных платежа.\r\n\r\nПараметры:\r\n- row — строка платежа с данными операции\r\n\r\nФункция:\r\n- получает данные платежа из строки;\r\n- проверяет заполненность обязательных полей;\r\n- проверяет, что сумма платежа не равна нулю;\r\n- выполняет проверку ИНН через регулярные выражения;\r\n- вызывает исключение при некорректных данных;"},"next":{"block":{"type":"write_log","id":"7%/(Ic=UOkdn9lPp]KVs","fields":{"FIELDVALUE1":"info"},"inputs":{"VALUE1":{"shadow":{"type":"text","id":"~G|jtD:`kR!yMcP(QpuB","fields":{"TEXT":""}},"block":{"type":"f_string","id":"7M!n{y7SVyX~)ecF04A[","extraState":{},"fields":{"TEXT":"Валидация данных платежа..."}}}},"next":{"block":{"type":"group_block","id":"JMfsvN.sVgx+_weCKgt,","fields":{"FIELDVALUE":"Базовые пременные"},"inputs":{"DO":{"block":{"type":"variables_set","id":"Ua![?-}qwvxDIv`B?0sT","fields":{"VAR":{"id":"Ak[:Ef9D~ZyYr3^brKGD"}},"inputs":{"VALUE":{"block":{"type":"get_dict_value","id":"XXT)P421RZ`}Jlr2D,{_","inputs":{"VALUE1":{"block":{"type":"variables_get","id":"Dw;O`!t*EY^WXnKtaA08","fields":{"VAR":{"id":"_/vg4^P)]TBw7}27jSv^"}}}},"VALUE2":{"shadow":{"type":"text","id":"^C2E{?Ro#q=DQU+b4mrG","fields":{"TEXT":""}},"block":{"type":"text","id":"5s43o5N7anD|?:T})5$l","fields":{"TEXT":"Дата"}}}}}}},"next":{"block":{"type":"variables_set","id":"ak.iL!t-=9^@usj!]:U;","fields":{"VAR":{"id":"-s7qni$X]*-L9NA.r~gY"}},"inputs":{"VALUE":{"block":{"type":"get_dict_value","id":"_0T1^$u5r-768yibsih@","inputs":{"VALUE1":{"block":{"type":"variables_get","id":"yyn0Y,[Iw|=dt[:NPSeD","fields":{"VAR":{"id":"_/vg4^P)]TBw7}27jSv^"}}}},"VALUE2":{"shadow":{"type":"text","id":"(4URx^U43_Jx%CE+MDWI","fields":{"TEXT":""}},"block":{"type":"text","id":"Uc(x!M+B%v,K~{AHk3!b","fields":{"TEXT":"Сумма"}}}}}}},"next":{"block":{"type":"variables_set","id":"?H7nO*V{Iorr_5J)!~H!","fields":{"VAR":{"id":"RR,qkAXttU(`7i8db=4|"}},"inputs":{"VALUE":{"block":{"type":"get_dict_value","id":"7ch2x3Uupb`6n8klHS]h","inputs":{"VALUE1":{"block":{"type":"variables_get","id":"=OkQD?m$7f~y+:ScHhE{","fields":{"VAR":{"id":"_/vg4^P)]TBw7}27jSv^"}}}},"VALUE2":{"shadow":{"type":"text","id":"qm8qu1mxbFuF_[@)3PNw","fields":{"TEXT":""}},"block":{"type":"text","id":"lVFhCY_:w}UAl!7Dqd$j","fields":{"TEXT":"ИНН_контрагента"}}}}}}},"next":{"block":{"type":"variables_set","id":"lWRu2nwr[d5S.Mnw$Gko","fields":{"VAR":{"id":"{.eDjfT}lMx@d$)CxF3/"}},"inputs":{"VALUE":{"block":{"type":"get_dict_value","id":"im:?t8sK/@Sw~GPmX:MN","inputs":{"VALUE1":{"block":{"type":"variables_get","id":"RDr*].0!~NG!M0Xiv%aU","fields":{"VAR":{"id":"_/vg4^P)]TBw7}27jSv^"}}}},"VALUE2":{"shadow":{"type":"text","id":"{4$nqYLm!4J*mSR^I{`8","fields":{"TEXT":""}},"block":{"type":"text","id":";VR$;8PLSFRIw!H1,[-X","fields":{"TEXT":"Организация"}}}}}}},"next":{"block":{"type":"variables_set","id":"]|XtE-6L/9G!Wq]q.=E}","fields":{"VAR":{"id":"GQuOgS:OP^}_`hVF88Se"}},"inputs":{"VALUE":{"block":{"type":"get_dict_value","id":":ALehh^o6Kl+6%io6XrM","inputs":{"VALUE1":{"block":{"type":"variables_get","id":"WF3n%|q1_B*^G*D]kqOn","fields":{"VAR":{"id":"_/vg4^P)]TBw7}27jSv^"}}}},"VALUE2":{"shadow":{"type":"text","id":"Z.7vSsMA[8M%4~9eF/pI","fields":{"TEXT":""}},"block":{"type":"text","id":"@/,s(yEd_Gnnq!y[[G]c","fields":{"TEXT":"Назначение"}}}}}}}}}}}}}}}}}},"next":{"block":{"type":"group_block","id":"12tsCby=mUE:O6xjORP9","fields":{"FIELDVALUE":"Валидация"},"inputs":{"DO":{"block":{"type":"controls_if","id":"lr~TgwJ+JbDwMR,,~B?e","inputs":{"IF0":{"block":{"type":"text_isEmpty","id":"Wc=FS4.GxV,m1Mu{9k{-","inputs":{"VALUE":{"shadow":{"type":"text","id":"2ewTC4oey%(`{r!W6:/n","fields":{"TEXT":""}},"block":{"type":"variables_get","id":"dmKFpR4E_l]taqPW!@7w","fields":{"VAR":{"id":"Ak[:Ef9D~ZyYr3^brKGD"}}}}}}},"DO0":{"block":{"type":"write_log","id":"j?TskU7KW5d7Q`Q=uv`i","fields":{"FIELDVALUE1":"error"},"inputs":{"VALUE1":{"shadow":{"type":"text","id":"]r/#_.Gx^CUNwT06#5h8","fields":{"TEXT":""}},"block":{"type":"text","id":"Y1u#_8u9s;7$XPSQ)IQ^","fields":{"TEXT":"Дата должна быть заполнена"}}}},"next":{"block":{"type":"call_raise","id":"bo7u`O/cCX@Ol@_Yl{pt","inputs":{"VALUE":{"shadow":{"type":"text","id":"RNTbarXXbBo0x{]9sOY#","fields":{"TEXT":""}},"block":{"type":"text","id":"4eP+4%`w|NH_(woD$+@Z","fields":{"TEXT":"Дата должна быть заполнена"}}}}}}}}},"next":{"block":{"type":"controls_if","id":"7v-tB0NMGu)XS!yqn+%L","inputs":{"IF0":{"block":{"type":"text_isEmpty","id":"]e)jTq+4Wm9xQiX3tSZ0","inputs":{"VALUE":{"shadow":{"type":"text","id":"n7,WT[ap=(RxJt9;ecM3","fields":{"TEXT":""}},"block":{"type":"variables_get","id":"$]c[{rio[KVi}X|bi]2#","fields":{"VAR":{"id":"GQuOgS:OP^}_`hVF88Se"}}}}}}},"DO0":{"block":{"type":"write_log","id":"brbI3=OLzv;78/v31r`+","fields":{"FIELDVALUE1":"error"},"inputs":{"VALUE1":{"shadow":{"type":"text","id":"D~.-/7]Cs@Y.d=qesT?1","fields":{"TEXT":""}},"block":{"type":"text","id":"GK.%uLYGTX](6.VYP~8%","fields":{"TEXT":"Назначение должно быть заполнено"}}}},"next":{"block":{"type":"call_raise","id":"%}+KH3AoKNX3YDG,R?5s","inputs":{"VALUE":{"shadow":{"type":"text","id":"@XblI}ZzYVXG2{zGN-iI","fields":{"TEXT":""}},"block":{"type":"text","id":"DLe1d1akEWFa9:5b%Qq4","fields":{"TEXT":"Назначение должно быть заполнено"}}}}}}}}},"next":{"block":{"type":"controls_if","id":"(3y)}5%RobFhOhYt_H,)","inputs":{"IF0":{"block":{"type":"text_isEmpty","id":"Rgi]Q2o@V$IEO(o*hQlD","inputs":{"VALUE":{"shadow":{"type":"text","id":"0(LMAx4.d%B)U5f1wVmS","fields":{"TEXT":""}},"block":{"type":"variables_get","id":"vSEU`a)R=Mm,Ce{bph`,","fields":{"VAR":{"id":"{.eDjfT}lMx@d$)CxF3/"}}}}}}},"DO0":{"block":{"type":"write_log","id":"mlhr!{j%p|%M~6$PDkF}","fields":{"FIELDVALUE1":"error"},"inputs":{"VALUE1":{"shadow":{"type":"text","id":"O{_L+{fZ}V|PGt8`[FRX","fields":{"TEXT":""}},"block":{"type":"text","id":"66G+-qYtpDm+jM8jb6E0","fields":{"TEXT":"Организация должна быть заполнена"}}}},"next":{"block":{"type":"call_raise","id":"g*Li}_Bu|iz,}9`ak.@6","inputs":{"VALUE":{"shadow":{"type":"text","id":"|0{ucCMQ*8.*bJm2I_k}","fields":{"TEXT":""}},"block":{"type":"text","id":"]-DWhM%hEI~.fBLa=ivg","fields":{"TEXT":"Организация должна быть заполнена"}}}}}}}}},"next":{"block":{"type":"controls_if","id":"+XnmZc$`?yrsD#uN,+L1","inputs":{"IF0":{"block":{"type":"logic_compare","id":"Jf+tXptS*:DV]TZI(MQH","fields":{"OP":"LTE"},"inputs":{"A":{"block":{"type":"variables_get","id":"Wp#hwBT6}mOJOJ[#-LXt","fields":{"VAR":{"id":"-s7qni$X]*-L9NA.r~gY"}}}},"B":{"block":{"type":"math_number","id":"v^a@x;8~b!S?yAI4NK.k","fields":{"NUM":0}}}}}},"DO0":{"block":{"type":"write_log","id":"%qmhliRgT[c!Cg]2jA*,","fields":{"FIELDVALUE1":"error"},"inputs":{"VALUE1":{"shadow":{"type":"text","id":"=G)Vg/p,WG,s[QXY08Ch","fields":{"TEXT":""}},"block":{"type":"text","id":"jD2;VMn{{@y9G%Su1t!e","fields":{"TEXT":"Сумма не должна равнятся нулю"}}}},"next":{"block":{"type":"call_raise","id":"QwKj4/UrXs1WFg5+xA]=","inputs":{"VALUE":{"shadow":{"type":"text","id":"E]`D]V1EK,Qfl`Puy+.}","fields":{"TEXT":""}},"block":{"type":"text","id":"cNkVXDWxSC94Z7cQzRq|","fields":{"TEXT":"Сумма не должна равнятся нулю"}}}}}}}}},"next":{"block":{"type":"controls_if","id":"t0ZEgI9ujaGXS3nXY(9Z","inputs":{"IF0":{"block":{"type":"logic_negate","id":"/6p=pK34F|N`E$+(E-]I","inputs":{"BOOL":{"block":{"type":"procedures_callreturn","id":"tB/N0Lk]8}Sk%f@G;1(3","extraState":{"name":"validate_by_regex","params":["value","pattern"]},"inputs":{"ARG0":{"block":{"type":"f_string","id":"$Qs50CMNak!}3Lzg2,%/","extraState":{},"fields":{"TEXT":"{inn}"}}},"ARG1":{"block":{"type":"text","id":"E4l[3OURUSiXrijgW}fY","fields":{"TEXT":"^\\d{10}(\\d{2})?$"}}}}}}}}},"DO0":{"block":{"type":"write_log","id":"u;9!L$7oDrlHV])#H9)=","fields":{"FIELDVALUE1":"error"},"inputs":{"VALUE1":{"shadow":{"type":"text","id":":|QxwxGALaOhGo;n33YR","fields":{"TEXT":""}},"block":{"type":"text","id":"OIt`e/0M$phuKNT3%Z}-","fields":{"TEXT":"ИНН некорректен"}}}},"next":{"block":{"type":"call_raise","id":"GOV_[.KmRbHn,=}!psFO","inputs":{"VALUE":{"shadow":{"type":"text","id":"Bh%`k^`?^2Htd9Od@Y+@","fields":{"TEXT":""}},"block":{"type":"text","id":"KFb9,O1nU3S8WcW,0q/q","fields":{"TEXT":"ИНН некорректен"}}}}}}}}}}}}}}}}}}}},"next":{"block":{"type":"write_log","id":"1OkFAB[J~-Ic~B=Ivs5/","fields":{"FIELDVALUE1":"info"},"inputs":{"VALUE1":{"shadow":{"type":"text","id":"c6I+M:hrWg]x`|)I?W{0","fields":{"TEXT":""}},"block":{"type":"f_string","id":"H-m$yyoQrjtdjA~DX%V=","extraState":{},"fields":{"TEXT":"Данные корректны"}}}}}}}}}}}}}}}},{"type":"procedures_defreturn","id":"!7`w`:-2]ITFu=HxBL(m","x":20,"y":2280,"extraState":{"procedureId":"KD3^{/ADRl/(12LJ@#tk"},"icons":{"comment":{"text":"Опишите эту функцию…","pinned":false,"height":80,"width":160}},"fields":{"NAME":"read_bank_statement"},"inputs":{"STACK":{"block":{"type":"comment_block","id":"ytmDEbvKG00|5NMs+:eA","fields":{"TEXT":"Выполняет чтение файла банковской выписки.\r\n\r\nФункция:\r\n- получает путь к файлу выписки из CONFIG;\r\n- проверяет существование файла;\r\n- определяет тип файла по расширению;\r\n- поддерживает чтение файлов:\r\n  - `.xlsx`\r\n  - `.csv`\r\n- считывает данные банковской выписки;\r\n- выполняет обработку ошибок чтения файла;\r\n- завершает выполнение программы при критических ошибках;\r\n- возвращает данные выписки `raw_statement`."},"next":{"block":{"type":"write_log","id":"E0zeLrKewV6(Gd=42;a.","fields":{"FIELDVALUE1":"info"},"inputs":{"VALUE1":{"shadow":{"type":"text","id":"/,2=yoH9SS3E.J%#hQ7r","fields":{"TEXT":""}},"block":{"type":"text","id":")0),+cb3^6^O!Yl}znGH","fields":{"TEXT":"Чтение файла банковской выписки..."}}}},"next":{"block":{"type":"group_block","id":":bE[8Ou._c^jwxZ:as^s","fields":{"FIELDVALUE":"Базовые пременные"},"inputs":{"DO":{"block":{"type":"variables_set","id":"RAe*,XYju~,-}/o(K9~p","fields":{"VAR":{"id":"irD!X.vYXFm/nrCsNxHU"}},"inputs":{"VALUE":{"block":{"type":"get_executable_path","id":"q]Mb$8EYT.+n+)jP-+1,","fields":{"FIELDVALUE1":true},"inputs":{"VALUE1":{"shadow":{"type":"text","id":"NZ+w][|OLe$|fHp-,qBE","fields":{"TEXT":""}},"block":{"type":"get_dict_value","id":"JQ{.acg@n_4Nu^UoPu#8","inputs":{"VALUE1":{"block":{"type":"use_constant","id":"QLw[IicK5sLXyvh=NT#j","fields":{"FIELDVALUE1":"CONFIG"}}},"VALUE2":{"shadow":{"type":"text","id":"qsbb*9i*fB}S.UUgs~9+","fields":{"TEXT":""}},"block":{"type":"text","id":"RLi%!dcg7K(]=t=s1RiY","fields":{"TEXT":"statement_file"}}}}}}}}}}}}},"next":{"block":{"type":"group_block","id":"=f*`JQ4.nafW.L*BtCdJ","fields":{"FIELDVALUE":"Входная проверка"},"inputs":{"DO":{"block":{"type":"controls_if","id":"[q*PKn5duH+xAL6BJ8h(","inputs":{"IF0":{"block":{"type":"logic_negate","id":"i@tN.$M8vznr~$BY,)w0","inputs":{"BOOL":{"block":{"type":"is_there_a_way_2","id":"F*7{To}Bh!PMUT1*7,6M","inputs":{"path_file":{"shadow":{"type":"text","id":",TuAZGRnx5/HeGp#T6`;","fields":{"TEXT":""}},"block":{"type":"variables_get","id":"eEla3m{Z38-a[Tmzi#lA","fields":{"VAR":{"id":"irD!X.vYXFm/nrCsNxHU"}}}}}}}}}},"DO0":{"block":{"type":"write_log","id":"*vQGpsKiBT2@zCq,x3EU","fields":{"FIELDVALUE1":"error"},"inputs":{"VALUE1":{"shadow":{"type":"text","id":"SjXTF)TAmef|uQ4[UZ0u","fields":{"TEXT":""}},"block":{"type":"text","id":"zqzZBuy%|pDru9=6y{sS","fields":{"TEXT":"Файл банковской выписки не найден"}}}},"next":{"block":{"type":"stop_robot","id":"HvhjV=[`j|lv~sF?csp^","inputs":{"VALUE1":{"shadow":{"type":"text","id":"hThr]/]#C@Z$eA}X*z!s","fields":{"TEXT":"Завершение работы робота"}}}}}}}}},"next":{"block":{"type":"write_log","id":"2=uVwrTT*O}D)aWzL4E5","fields":{"FIELDVALUE1":"info"},"inputs":{"VALUE1":{"shadow":{"type":"text","id":"W/EHZ,x(4^96.js;+E7l","fields":{"TEXT":""}},"block":{"type":"text","id":"[?2;vDBnBU!7WDB$?=j~","fields":{"TEXT":"Файл банковской выписки найден"}}}}}}}}},"next":{"block":{"type":"group_block","id":";=Xl|HQMLd-3+2U1uTfh","fields":{"FIELDVALUE":"Чтение файла"},"inputs":{"DO":{"block":{"type":"variables_set","id":"Ky8(ql4WgvHXdy;;+95#","fields":{"VAR":{"id":"8?~QZELuwqvvZPWbIqjE"}},"inputs":{"VALUE":{"block":{"type":"logic_boolean","id":"+J-5O$8M[)Ozki`q,3j0","fields":{"BOOL":"FALSE"}}}},"next":{"block":{"type":"variables_set","id":"111_^]4w5fWeuDRz,pR*","icons":{"comment":{"text":"Присваивает переменной значение вставки","pinned":false,"height":74,"width":211}},"fields":{"VAR":{"id":"H=r^kne);,^=u#UCvgNd"}},"inputs":{"VALUE":{"block":{"type":"get_file_metadata","id":"R+k%kZFsB2TVu=D7fx%_","fields":{"FIELDVALUE1":"file_extension"},"inputs":{"path_file":{"shadow":{"type":"text","id":"YhXB!dKZe-4^pl*rKyob","fields":{"TEXT":""}},"block":{"type":"variables_get","id":"EIiIPYL6~OF@),#J=*c5","fields":{"VAR":{"id":"irD!X.vYXFm/nrCsNxHU"}}}}}}}},"next":{"block":{"type":"try_except","id":"(-jt(H5+z`+P|W25C%@L","inputs":{"try":{"block":{"type":"controls_if","id":"yGXtommk~#U_#==9TM1x","inputs":{"IF0":{"block":{"type":"logic_compare","id":"4DU*Qlm7hPH{jGW*5Vj-","fields":{"OP":"EQ"},"inputs":{"A":{"block":{"type":"variables_get","id":"(lrSYw@5T4qAf@#UuStr","fields":{"VAR":{"id":"H=r^kne);,^=u#UCvgNd"}}}},"B":{"block":{"type":"text","id":"reC3dMdM/Lf$7{Kf_pV6","fields":{"TEXT":"xlsx"}}}}}},"DO0":{"block":{"type":"variables_set","id":"O:-NU+q49uvZ5k2b1YKo","icons":{"comment":{"text":"Присваивает переменной значение вставки","pinned":false,"height":74,"width":211}},"fields":{"VAR":{"id":"aS}c{;1cEiVjh7Y#/YkT"}},"inputs":{"VALUE":{"block":{"type":"excel_read_excel_new","id":"cucRp?8urr3VN$}GYX0M","fields":{"dictionaty_key_excel":"False"},"inputs":{"path_file":{"shadow":{"type":"text","id":"AC*ea]CgDZyN`4tf2XwS","fields":{"TEXT":""}},"block":{"type":"variables_get","id":"ucp,3fCwW?[.g|VHKj5a","fields":{"VAR":{"id":"irD!X.vYXFm/nrCsNxHU"}}}},"list":{"shadow":{"type":"text","id":"XC[:c%^)DWrw|1[FaCBR","fields":{"TEXT":""}},"block":{"type":"math_number","id":".aUpM/b=oM?g1,`wxkm.","fields":{"NUM":1}}},"column_dtypes":{"shadow":{"type":"logic_null","id":"@E^E^X(m$f@lLd@J1`Rq"}}}}}},"next":{"block":{"type":"variables_set","id":"5`ZZs3av/J;!I?f{r}uM","fields":{"VAR":{"id":"8?~QZELuwqvvZPWbIqjE"}},"inputs":{"VALUE":{"block":{"type":"logic_boolean","id":"***X-%:H/{X@8{{DtC}_","fields":{"BOOL":"TRUE"}}}}}}}}},"next":{"block":{"type":"controls_if","id":"MFs3dCG0zu}y/1_Ba[RD","inputs":{"IF0":{"block":{"type":"logic_compare","id":"P]@HH|@mV]6wjq(RT?%?","fields":{"OP":"EQ"},"inputs":{"A":{"block":{"type":"variables_get","id":"E^K[G+:di:/CFU*|aZUO","fields":{"VAR":{"id":"H=r^kne);,^=u#UCvgNd"}}}},"B":{"block":{"type":"text","id":"-OZaY4nol[YF:G`jzW4v","fields":{"TEXT":"csv"}}}}}},"DO0":{"block":{"type":"variables_set","id":"A_lcmKff2UZ}8U~YNVd;","icons":{"comment":{"text":"Присваивает переменной значение вставки","pinned":false,"height":74,"width":211}},"fields":{"VAR":{"id":"aS}c{;1cEiVjh7Y#/YkT"}},"inputs":{"VALUE":{"block":{"type":"read_file_3","id":"N3?6H8a1-DYp@O%CV6`)","extraState":"<mutation read_file_type=\"csv\"></mutation>","fields":{"fieldsCount":"csv","FIELDVALUE1":",","CSV_ENGINE":"pandas","CSV_HEADERS_MODE":"True"},"inputs":{"path":{"shadow":{"type":"text","id":"Ex/hcGVhPT%EKuD}z|bZ","fields":{"TEXT":""}},"block":{"type":"variables_get","id":"mDp/U]NnisXq8|H,YVf-","fields":{"VAR":{"id":"irD!X.vYXFm/nrCsNxHU"}}}},"encoding":{"shadow":{"type":"text","id":"k`R-!HWF9g%9pKj3YWs#","fields":{"TEXT":"utf-8"}}},"USECOLS":{"shadow":{"type":"logic_null","id":"UrhF(!iamX1H?E$nOgH4"}},"SKIPROWS":{"shadow":{"type":"logic_null","id":"V%+N)^v[/USL|2Dh%uB("}},"NROWS":{"shadow":{"type":"logic_null","id":"=~P;87Lo=G4trg=#-%/H"}},"COLUMN_DTYPES":{"shadow":{"type":"logic_null","id":"jZhpPEUVF|TcDN?o=$,t"}}}}}},"next":{"block":{"type":"variables_set","id":"~+lR*~91*$abu4+_/?eV","fields":{"VAR":{"id":"8?~QZELuwqvvZPWbIqjE"}},"inputs":{"VALUE":{"block":{"type":"logic_boolean","id":"LntSuK-)VF`)LrouA_=t","fields":{"BOOL":"TRUE"}}}}}}}}},"next":{"block":{"type":"controls_if","id":"w!6942$P,oyTY==dr8_Z","inputs":{"IF0":{"block":{"type":"logic_compare","id":"En|RL[xIOKNray/,fwox","fields":{"OP":"EQ"},"inputs":{"A":{"block":{"type":"variables_get","id":"^4I[^`5M8mNZf]H.4KA;","fields":{"VAR":{"id":"H=r^kne);,^=u#UCvgNd"}}}},"B":{"block":{"type":"text","id":"EDSF.}LLKnF~aRm$ro1H","fields":{"TEXT":"json"}}}}}},"DO0":{"block":{"type":"variables_set","id":"0ezx6[}2N|l-e.H.bdF8","icons":{"comment":{"text":"Присваивает переменной значение вставки","pinned":false,"height":74,"width":211}},"fields":{"VAR":{"id":"aS}c{;1cEiVjh7Y#/YkT"}},"inputs":{"VALUE":{"block":{"type":"read_file_3","id":";]5KG5h]+M-QzZB{x9{C","extraState":"<mutation read_file_type=\"json\"></mutation>","fields":{"fieldsCount":"json"},"inputs":{"path":{"shadow":{"type":"text","id":"XNdQGOCpO7(bL8Ks!HTr","fields":{"TEXT":""}},"block":{"type":"variables_get","id":"t[9d]oUtI:av^moIJf2h","fields":{"VAR":{"id":"irD!X.vYXFm/nrCsNxHU"}}}},"encoding":{"shadow":{"type":"text","id":"WV0?pnA{-7|7V$5me-]h","fields":{"TEXT":"utf-8"}}}}}}},"next":{"block":{"type":"variables_set","id":"f|o9%Zuq=Zd6~g^VD{w:","icons":{"comment":{"text":"Присваивает переменной значение вставки","pinned":false,"height":74,"width":211}},"fields":{"VAR":{"id":"aS}c{;1cEiVjh7Y#/YkT"}},"inputs":{"VALUE":{"block":{"type":"create_df","id":"*8.Ti~HC=WK%f%U?crvb","inputs":{"dict_value":{"block":{"type":"variables_get","id":"WDGt{#j_C^**A4C4@ZpQ","fields":{"VAR":{"id":"aS}c{;1cEiVjh7Y#/YkT"}}}}}}}},"next":{"block":{"type":"variables_set","id":"vMa4W2+@J4ze#ru,8(-R","fields":{"VAR":{"id":"8?~QZELuwqvvZPWbIqjE"}},"inputs":{"VALUE":{"block":{"type":"logic_boolean","id":"Of]N{MIj3D3oAqLJj*D^","fields":{"BOOL":"TRUE"}}}}}}}}}}},"next":{"block":{"type":"controls_if","id":"](f8_JdOsj!LJ6,D4z!w","inputs":{"IF0":{"block":{"type":"logic_negate","id":"lil(FXK:((|KOSdB0[L:","inputs":{"BOOL":{"block":{"type":"variables_get","id":"ok:XvNw%)4Ic{/4phor.","fields":{"VAR":{"id":"8?~QZELuwqvvZPWbIqjE"}}}}}}},"DO0":{"block":{"type":"write_log","id":"TLvk#6qsKKHSnuJ-3A?N","fields":{"FIELDVALUE1":"error"},"inputs":{"VALUE1":{"shadow":{"type":"text","id":"}0V-Z`4jxUbLg*9V%8ll","fields":{"TEXT":""}},"block":{"type":"text","id":"+Qf]0E17f7/@a.!]HGJN","fields":{"TEXT":"Ошибка чтения файла банковской выписки"}}}},"next":{"block":{"type":"stop_robot","id":"9w{D5?Gh)f`^~*?M@,w[","inputs":{"VALUE1":{"shadow":{"type":"text","id":"K]5Jj49^gtWQOsKC;NXz","fields":{"TEXT":"Завершение работы робота"}}}}}}}}}}}}}}}}},"except":{"block":{"type":"write_log","id":"5bm}T;GxgqqXD?p;9T0c","fields":{"FIELDVALUE1":"error"},"inputs":{"VALUE1":{"shadow":{"type":"text","id":")(Me[BQ@a_;whu}jJl55","fields":{"TEXT":""}},"block":{"type":"text","id":"ULrCSNoUlWi06tLBqN`Q","fields":{"TEXT":"Ошибка чтения файла банковской выписки"}}}},"next":{"block":{"type":"stop_robot","id":"94iI{-l]Ovz=?Cb2t!W1","inputs":{"VALUE1":{"shadow":{"type":"text","id":"RD($f9c_%DOMxKvj}Z@m","fields":{"TEXT":"Завершение работы робота"}}}}}}}},"error_description":{"block":{"type":"variables_get","id":"okk*=_8ZhRHCw?BBIzBW","fields":{"VAR":{"id":"K]^/?eL95JR*u}.NU7L("}}}}},"next":{"block":{"type":"write_log","id":"PQupbict[QQ;YMj{odaR","fields":{"FIELDVALUE1":"info"},"inputs":{"VALUE1":{"shadow":{"type":"text","id":"_|{0gTj_{[LLd$da{bZV","fields":{"TEXT":""}},"block":{"type":"text","id":"RF)8~AZx3bY+88%Eqchh","fields":{"TEXT":"Чтение банковской выписки успешно"}}}}}}}}}}}}},"next":{"block":{"type":"group_block","id":"l,#5.rN!d1N2x+C.aE3+","fields":{"FIELDVALUE":"Валидация данных"},"inputs":{"DO":{"block":{"type":"procedures_callnoreturn","id":"-aTGo1OJ)_Ih7Av!%m[6","extraState":{"name":"validate_bank_statement","params":["statement"]},"inputs":{"ARG0":{"block":{"type":"variables_get","id":"`]7bhlWpp|WHe@QUOnSj","fields":{"VAR":{"id":"aS}c{;1cEiVjh7Y#/YkT"}}}}}}}},"next":{"block":{"type":"write_log","id":"JRgIKyD35K^:}cO%[z1p","fields":{"FIELDVALUE1":"info"},"inputs":{"VALUE1":{"shadow":{"type":"text","id":"A^Vy{.T$*q*,plY@#!Mt","fields":{"TEXT":""}},"block":{"type":"text","id":"GyAKbb#hnJjfgriCK1t*","fields":{"TEXT":"Банковская выписка готова к работе"}}}}}}}}}}}}}}}}}},"RETURN":{"block":{"type":"variables_get","id":"ZZMZS1-*t?D!aTd{vv(N","fields":{"VAR":{"id":"aS}c{;1cEiVjh7Y#/YkT"}}}}}}]},"variables":[{"name":"value","id":"p`a-ZY/1_BAC}wTk*]%1","global":false},{"name":"pattern","id":"m;F[q_2tveGoFelpKGjz","global":false},{"name":"config_path","id":"o(4KrG#~FOUyEUw|({w2","global":false},{"name":"config","id":"=cnGp7w^(zc|[v+6$0!/","global":false},{"name":"statement","id":"%9v@:^Vx-]2?^Zi%Tcv}","global":false},{"name":"row","id":"_/vg4^P)]TBw7}27jSv^","global":false},{"name":"payment","id":"d5f^:-h;moNE(c|j!a,2","global":false},{"name":"total_count","id":"2rZUQ%weKke.FYdg~}(*","global":false},{"name":"success_count","id":"N.q!}r#YUwK.j7(e2m_y","global":false},{"name":"error_count","id":"?Uh[i#l8W$2zs[HXGe^U","global":false},{"name":"duplicate_count","id":"6nDmXZu$Nj_?)P[}F+Lf","global":false},{"name":"skipped_count","id":"s{ILW{ydH!mUH!BiBa*q","global":false},{"name":"results","id":"f[hwD?_=SHxkc]Zm^rjC","global":false},{"name":"document_ref","id":"$V8eK:GAwlczn~4LCty5","global":false},{"name":"status","id":"19Q.ax@f[XGIaT=,t3z4","global":false},{"name":"message","id":"`BK[nI-yfFhd[3],D:yF","global":false},{"name":"document_type","id":".Kwkhl$,J3fe(?Z_w}b{","global":false},{"name":"statement_path","id":"irD!X.vYXFm/nrCsNxHU","global":false},{"name":"raw_statement","id":"aS}c{;1cEiVjh7Y#/YkT","global":false},{"name":"statement_file_type","id":"H=r^kne);,^=u#UCvgNd","global":false},{"name":"error_description","id":"K]^/?eL95JR*u}.NU7L(","global":false},{"name":"is_read","id":"8?~QZELuwqvvZPWbIqjE","global":false},{"name":"date","id":"Ak[:Ef9D~ZyYr3^brKGD","global":false},{"name":"amount","id":"-s7qni$X]*-L9NA.r~gY","global":false},{"name":"inn","id":"RR,qkAXttU(`7i8db=4|","global":false},{"name":"organization","id":"{.eDjfT}lMx@d$)CxF3/","global":false},{"name":"purpose","id":"GQuOgS:OP^}_`hVF88Se","global":false},{"name":"raw_type","id":"w8WPv#Ht@]Jf08+Ym|3W","global":false},{"name":"required_columns","id":"(W.XicDr)K8pasW5op.y","global":false},{"name":"column","id":"MKoy}V;0qs@|B2tb1[4L","global":false},{"name":"columns","id":"%fM.Cf@lHUEcY$B#9+JD","global":false},{"name":"count","id":"+MiW%nzLA[a{Y`?W2#A5","global":false}],"procedures":[{"id":"45UsdLdvQJUcTj~oJ)AF","name":"load_config","returnTypes":[]},{"id":"6W[(hB4r1bY?S8KH@EWt","name":"validate_by_regex","returnTypes":[],"parameters":[{"id":"G$:FBZ~]2]LA(7t$|YBd","name":"value"},{"id":"nc$8#n9DcZ1E)9cx69M~","name":"pattern"}]},{"id":"hn|L/^+|x)#saX3G|5i9","name":"read_config","returnTypes":[],"parameters":[{"id":"G2`E,@.IC@,t2#*h6*^Q","name":"config_path"}]},{"id":"9v2,0Zt|FdK;vtYjXeQ3","name":"prepare_config","returnTypes":[],"parameters":[{"id":".7flw)J~]3%/{et/`ZhT","name":"config"}]},{"id":"KD3^{/ADRl/(12LJ@#tk","name":"read_bank_statement","returnTypes":[]},{"id":"Ih5!k9+Fw?I6be,p}+@$","name":"validate_bank_statement","returnTypes":null,"parameters":[{"id":"hx-5v#m`45Dpqs`3ovV*","name":"statement"}]},{"id":"v?m+zr|}6[5e6`.}tvpe","name":"validate_payment_row","returnTypes":null,"parameters":[{"id":"oI2MQVRsCOkByXErb[C7","name":"row"}]},{"id":"nEJ/S!1pz7W[Y;%;F(g4","name":"define_operation_type","returnTypes":[],"parameters":[{"id":"{1/|[0[$0y{N4/[bEU*T","name":"payment"}]},{"id":"pl+I}h]=.A=#{FV=V|/B","name":"finalize_processing","returnTypes":null,"parameters":[{"id":"2h+/3@WdSkT]RyT63c1C","name":"total_count"},{"id":"?nlUoSG#]UPA*S(ci?Kf","name":"success_count"},{"id":"p.rr`iAn*^bxf|A@XXf`","name":"error_count"},{"id":"6C9}WD.U)m=aF:@R0%8Y","name":"duplicate_count"}]},{"id":"SNLHSK}5M%oWt0[i;~6u","name":"process_statement_rows","returnTypes":null,"parameters":[{"id":"ZH^_N_2GiEqjSBFfuLEG","name":"statement"}]},{"id":"z%;g~7T%[k4mY5frPlf5","name":"save_report","returnTypes":null,"parameters":[{"id":"CdQmhwQbv%3=mSH6:A/6","name":"results"}]},{"id":"7cmH|u=H@uqLgf|(kV.Q","name":"add_result","returnTypes":null,"parameters":[{"id":"vp$OUw~l3iAiJA3OD`P.","name":"results"},{"id":"xdkZ5EFK[u,|_k};cPVT","name":"payment"},{"id":"5z%LwqEaLG1dR6sz(yy}","name":"status"},{"id":"nCBj-?L:m;y2f6!DpP?N","name":"message"},{"id":"+hTbj)|$_8qi`q!i::$p","name":"document_ref"}]},{"id":"1JQ4F#F!OU+fRY3Q@N(;","name":"open_1c_web","returnTypes":[]},{"id":"K~J/AscGhGenhzsdG7Zx","name":"login_1c_web","returnTypes":null},{"id":"^;SAvoJ:k%LB^@VWS7o_","name":"open_bank_statements_table_web","returnTypes":null},{"id":"oc*12J.{|JZ?CM85O~hK","name":"create_1c_document","returnTypes":null,"parameters":[{"id":"6qEMbyO+e7g:gH$lh.^x","name":"payment"},{"id":"GZ(Z}`0Cl8LpJCNO.Gp2","name":"document_type"},{"id":".Ej(j09k*nD81mC@Rx~N","name":"count"}]},{"id":"[o$[CZS6{8W`Atp}5Sv0","name":"get_document_link_1c","returnTypes":[],"parameters":[{"id":"JrX(w/8?pf8i)@%9g7v|","name":"payment"}]},{"id":"=o}Cttb{=C#@Y5{V,+Ap","name":"find_document_1c","returnTypes":[],"parameters":[{"id":"3+$8{)BnQYr1#^_qq*L2","name":"payment"}]},{"id":"d_W1Rn]$_Sh$l7HtNH7x","name":"check_duplicate","returnTypes":[],"parameters":[{"id":"9|+X|b7Ee?1uK/{^,3x}","name":"payment"}]}]},"dataStorage":{"webUiStorage":{}}},"workspaceModified":{"version":"3.0.3","workspace":{"blocks":{"languageVersion":0,"blocks":[{"type":"procedures_defnoreturn","id":"kY65@m^WH1^^gypO8ZnJ","x":1209,"y":2261,"extraState":{"procedureId":"Ih5!k9+Fw?I6be,p}+@$"},"icons":{"comment":{"text":"Опишите эту функцию…","pinned":false,"height":80,"width":160}},"fields":{"NAME":"validate_bank_statement"},"inputs":{"STACK":{"block":{"type":"comment_block","id":"Jg5N*a`3dI,B9zEFiU0C","fields":{"TEXT":"Выполняет проверку структуры банковской выписки.\r\n\r\nПараметры:\r\n- statement — DataFrame с данными банковской выписки\r\n\r\nФункция:\r\n- проверяет наличие обязательных колонок в DataFrame;\r\n- завершает выполнение программы при отсутствии обязательных колонок;"},"next":{"block":{"type":"write_log","id":"NrxS.jdyOE:Q~h5H;g}I","fields":{"FIELDVALUE1":"info"},"inputs":{"VALUE1":{"shadow":{"type":"text","id":"BqDw)jzc:@Xw2D0F}-VB","fields":{"TEXT":""}},"block":{"type":"text","id":"mbGsTWFMb_%Bk~(gOmBJ","fields":{"TEXT":"Валидация банковской выписки..."}}}},"next":{"block":{"type":"group_block","id":"!v)h/4eo[]f5a5Cjfj|/","fields":{"FIELDVALUE":"Базовые пременные"},"inputs":{"DO":{"block":{"type":"variables_set","id":"dnZy8#x]o=i,}um5N$xZ","fields":{"VAR":{"id":"(W.XicDr)K8pasW5op.y"}},"inputs":{"VALUE":{"block":{"type":"lists_create_with","id":".17ULWGxJi?dB6[Soc:K","extraState":{"itemCount":6},"inputs":{"ADD0":{"block":{"type":"text","id":"Hkk_Ie$LI*$IS;x4cPM]","fields":{"TEXT":"Дата"}}},"ADD1":{"block":{"type":"text","id":"RWG$QvCD?7/`]{qx9U#7","fields":{"TEXT":"Сумма"}}},"ADD2":{"block":{"type":"text","id":"(ArH~dUo~{bo`uA/;QnJ","fields":{"TEXT":"Тип"}}},"ADD3":{"block":{"type":"text","id":"vAB5heK0T1N4`$(byHhV","fields":{"TEXT":"Назначение"}}},"ADD4":{"block":{"type":"text","id":"=UmIkdW;mZu^F?QQK_r]","fields":{"TEXT":"ИНН_контрагента"}}},"ADD5":{"block":{"type":"text","id":",@z$Hqs?-/B[vwn{|t7+","fields":{"TEXT":"Организация"}}}}}}},"next":{"block":{"type":"variables_set","id":"nnl`~rmf@3=tOGdsOw%m","icons":{"comment":{"text":"Присваивает переменной значение вставки","pinned":false,"height":74,"width":211,"bubbleRelLeft":-52.75,"bubbleRelTop":-98}},"fields":{"VAR":{"id":"%fM.Cf@lHUEcY$B#9+JD"}},"inputs":{"VALUE":{"block":{"type":"get_df_columns","id":"lu0DAr0,IG/ue,PWa]=:","inputs":{"VALUE1":{"block":{"type":"variables_get","id":"uWE2.E+j|4#7/s.x@PLU","fields":{"VAR":{"id":"%9v@:^Vx-]2?^Zi%Tcv}"}}}}}}}}}}}}},"next":{"block":{"type":"group_block","id":"X;00kkkx1BwF[GD)YDh5","fields":{"FIELDVALUE":"Проверка полей конфига"},"inputs":{"DO":{"block":{"type":"controls_forEach","id":"7!kuB$~T1N(pHoxaCuKg","fields":{"VAR":{"id":"MKoy}V;0qs@|B2tb1[4L"}},"inputs":{"LIST":{"block":{"type":"variables_get","id":"Ip5u6pEKy?gJ,^Bc!:uk","fields":{"VAR":{"id":"(W.XicDr)K8pasW5op.y"}}}},"DO":{"block":{"type":"controls_if","id":"S?PO(Fo%a5a;jL+/^Txw","inputs":{"IF0":{"block":{"type":"logic_compare","id":"xfPYNvy5ET5$1IC%#(mo","fields":{"OP":"EQ"},"inputs":{"A":{"block":{"type":"lists_indexOf","id":"v*KVPx^9iGr:/)hhq(c~","fields":{"END":"FIRST"},"inputs":{"VALUE":{"block":{"type":"variables_get","id":"!5nWxKxd*MeVb[oNaq}C","fields":{"VAR":{"id":"%fM.Cf@lHUEcY$B#9+JD"}}}},"FIND":{"block":{"type":"variables_get","id":":_i!U+1^M;?Op~*)$E,M","fields":{"VAR":{"id":"MKoy}V;0qs@|B2tb1[4L"}}}}}}},"B":{"block":{"type":"math_number","id":"yI[q+4==0@[DM(x9afdT","fields":{"NUM":-1}}}}}},"DO0":{"block":{"type":"write_log","id":"VpCX,yHWBcx@!YD@gWrN","fields":{"FIELDVALUE1":"error"},"inputs":{"VALUE1":{"shadow":{"type":"text","id":"n+8~IG[)#4_+=y*(To%`","fields":{"TEXT":""}},"block":{"type":"f_string","id":"5U}UTSj(sTy.Qj$|S0Yl","extraState":{},"fields":{"TEXT":"В банковской выпеске отсутсвует колонка: {column}"}}}},"next":{"block":{"type":"stop_robot","id":"V8fN/{WY)sy[(!Yx?FFN","inputs":{"VALUE1":{"shadow":{"type":"text","id":"+}/6+K`y9]?^KU.u4_`,","fields":{"TEXT":"Завершение работы робота"}}}}}}}}}}}},"next":{"block":{"type":"write_log","id":"E(1jMvS$G-z,%}Ge?|T2","fields":{"FIELDVALUE1":"info"},"inputs":{"VALUE1":{"shadow":{"type":"text","id":"(qth4J#/Tk^w_YtJuUJI","fields":{"TEXT":""}},"block":{"type":"text","id":"@IhYqSw%DY:]X4eg?;sF","fields":{"TEXT":"Все обязательные колонки в банковской выпеске существуют"}}}}}}}}}}}}}}}}}}},{"type":"procedures_defnoreturn","id":"S9*(aPY^T9zqDW!5S;MT","x":1214,"y":3108,"extraState":{"procedureId":"v?m+zr|}6[5e6`.}tvpe"},"icons":{"comment":{"text":"Опишите эту функцию…","pinned":false,"height":80,"width":160}},"fields":{"NAME":"validate_payment_row"},"inputs":{"STACK":{"block":{"type":"comment_block","id":"IBvm?dZByBk9a)tw,B`z","fields":{"TEXT":"Выполняет валидацию данных платежа.\r\n\r\nПараметры:\r\n- row — строка платежа с данными операции\r\n\r\nФункция:\r\n- получает данные платежа из строки;\r\n- проверяет заполненность обязательных полей;\r\n- проверяет, что сумма платежа не равна нулю;\r\n- выполняет проверку ИНН через регулярные выражения;\r\n- вызывает исключение при некорректных данных;"},"next":{"block":{"type":"write_log","id":"7%/(Ic=UOkdn9lPp]KVs","fields":{"FIELDVALUE1":"info"},"inputs":{"VALUE1":{"shadow":{"type":"text","id":"~G|jtD:`kR!yMcP(QpuB","fields":{"TEXT":""}},"block":{"type":"f_string","id":"7M!n{y7SVyX~)ecF04A[","extraState":{},"fields":{"TEXT":"Валидация данных платежа..."}}}},"next":{"block":{"type":"group_block","id":"JMfsvN.sVgx+_weCKgt,","fields":{"FIELDVALUE":"Базовые пременные"},"inputs":{"DO":{"block":{"type":"variables_set","id":"Ua![?-}qwvxDIv`B?0sT","fields":{"VAR":{"id":"Ak[:Ef9D~ZyYr3^brKGD"}},"inputs":{"VALUE":{"block":{"type":"get_dict_value","id":"XXT)P421RZ`}Jlr2D,{_","inputs":{"VALUE1":{"block":{"type":"variables_get","id":"Dw;O`!t*EY^WXnKtaA08","fields":{"VAR":{"id":"_/vg4^P)]TBw7}27jSv^"}}}},"VALUE2":{"shadow":{"type":"text","id":"^C2E{?Ro#q=DQU+b4mrG","fields":{"TEXT":""}},"block":{"type":"text","id":"5s43o5N7anD|?:T})5$l","fields":{"TEXT":"Дата"}}}}}}},"next":{"block":{"type":"variables_set","id":"ak.iL!t-=9^@usj!]:U;","fields":{"VAR":{"id":"-s7qni$X]*-L9NA.r~gY"}},"inputs":{"VALUE":{"block":{"type":"get_dict_value","id":"_0T1^$u5r-768yibsih@","inputs":{"VALUE1":{"block":{"type":"variables_get","id":"yyn0Y,[Iw|=dt[:NPSeD","fields":{"VAR":{"id":"_/vg4^P)]TBw7}27jSv^"}}}},"VALUE2":{"shadow":{"type":"text","id":"(4URx^U43_Jx%CE+MDWI","fields":{"TEXT":""}},"block":{"type":"text","id":"Uc(x!M+B%v,K~{AHk3!b","fields":{"TEXT":"Сумма"}}}}}}},"next":{"block":{"type":"variables_set","id":"?H7nO*V{Iorr_5J)!~H!","fields":{"VAR":{"id":"RR,qkAXttU(`7i8db=4|"}},"inputs":{"VALUE":{"block":{"type":"get_dict_value","id":"7ch2x3Uupb`6n8klHS]h","inputs":{"VALUE1":{"block":{"type":"variables_get","id":"=OkQD?m$7f~y+:ScHhE{","fields":{"VAR":{"id":"_/vg4^P)]TBw7}27jSv^"}}}},"VALUE2":{"shadow":{"type":"text","id":"qm8qu1mxbFuF_[@)3PNw","fields":{"TEXT":""}},"block":{"type":"text","id":"lVFhCY_:w}UAl!7Dqd$j","fields":{"TEXT":"ИНН_контрагента"}}}}}}},"next":{"block":{"type":"variables_set","id":"lWRu2nwr[d5S.Mnw$Gko","fields":{"VAR":{"id":"{.eDjfT}lMx@d$)CxF3/"}},"inputs":{"VALUE":{"block":{"type":"get_dict_value","id":"im:?t8sK/@Sw~GPmX:MN","inputs":{"VALUE1":{"block":{"type":"variables_get","id":"RDr*].0!~NG!M0Xiv%aU","fields":{"VAR":{"id":"_/vg4^P)]TBw7}27jSv^"}}}},"VALUE2":{"shadow":{"type":"text","id":"{4$nqYLm!4J*mSR^I{`8","fields":{"TEXT":""}},"block":{"type":"text","id":";VR$;8PLSFRIw!H1,[-X","fields":{"TEXT":"Организация"}}}}}}},"next":{"block":{"type":"variables_set","id":"]|XtE-6L/9G!Wq]q.=E}","fields":{"VAR":{"id":"GQuOgS:OP^}_`hVF88Se"}},"inputs":{"VALUE":{"block":{"type":"get_dict_value","id":":ALehh^o6Kl+6%io6XrM","inputs":{"VALUE1":{"block":{"type":"variables_get","id":"WF3n%|q1_B*^G*D]kqOn","fields":{"VAR":{"id":"_/vg4^P)]TBw7}27jSv^"}}}},"VALUE2":{"shadow":{"type":"text","id":"Z.7vSsMA[8M%4~9eF/pI","fields":{"TEXT":""}},"block":{"type":"text","id":"@/,s(yEd_Gnnq!y[[G]c","fields":{"TEXT":"Назначение"}}}}}}}}}}}}}}}}}},"next":{"block":{"type":"group_block","id":"12tsCby=mUE:O6xjORP9","fields":{"FIELDVALUE":"Валидация"},"inputs":{"DO":{"block":{"type":"controls_if","id":"lr~TgwJ+JbDwMR,,~B?e","inputs":{"IF0":{"block":{"type":"text_isEmpty","id":"Wc=FS4.GxV,m1Mu{9k{-","inputs":{"VALUE":{"shadow":{"type":"text","id":"2ewTC4oey%(`{r!W6:/n","fields":{"TEXT":""}},"block":{"type":"variables_get","id":"dmKFpR4E_l]taqPW!@7w","fields":{"VAR":{"id":"Ak[:Ef9D~ZyYr3^brKGD"}}}}}}},"DO0":{"block":{"type":"write_log","id":"j?TskU7KW5d7Q`Q=uv`i","fields":{"FIELDVALUE1":"error"},"inputs":{"VALUE1":{"shadow":{"type":"text","id":"]r/#_.Gx^CUNwT06#5h8","fields":{"TEXT":""}},"block":{"type":"text","id":"Y1u#_8u9s;7$XPSQ)IQ^","fields":{"TEXT":"Дата должна быть заполнена"}}}},"next":{"block":{"type":"call_raise","id":"bo7u`O/cCX@Ol@_Yl{pt","inputs":{"VALUE":{"shadow":{"type":"text","id":"RNTbarXXbBo0x{]9sOY#","fields":{"TEXT":""}},"block":{"type":"text","id":"4eP+4%`w|NH_(woD$+@Z","fields":{"TEXT":"Дата должна быть заполнена"}}}}}}}}},"next":{"block":{"type":"controls_if","id":"7v-tB0NMGu)XS!yqn+%L","inputs":{"IF0":{"block":{"type":"text_isEmpty","id":"]e)jTq+4Wm9xQiX3tSZ0","inputs":{"VALUE":{"shadow":{"type":"text","id":"n7,WT[ap=(RxJt9;ecM3","fields":{"TEXT":""}},"block":{"type":"variables_get","id":"$]c[{rio[KVi}X|bi]2#","fields":{"VAR":{"id":"GQuOgS:OP^}_`hVF88Se"}}}}}}},"DO0":{"block":{"type":"write_log","id":"brbI3=OLzv;78/v31r`+","fields":{"FIELDVALUE1":"error"},"inputs":{"VALUE1":{"shadow":{"type":"text","id":"D~.-/7]Cs@Y.d=qesT?1","fields":{"TEXT":""}},"block":{"type":"text","id":"GK.%uLYGTX](6.VYP~8%","fields":{"TEXT":"Назначение должно быть заполнено"}}}},"next":{"block":{"type":"call_raise","id":"%}+KH3AoKNX3YDG,R?5s","inputs":{"VALUE":{"shadow":{"type":"text","id":"@XblI}ZzYVXG2{zGN-iI","fields":{"TEXT":""}},"block":{"type":"text","id":"DLe1d1akEWFa9:5b%Qq4","fields":{"TEXT":"Назначение должно быть заполнено"}}}}}}}}},"next":{"block":{"type":"controls_if","id":"(3y)}5%RobFhOhYt_H,)","inputs":{"IF0":{"block":{"type":"text_isEmpty","id":"Rgi]Q2o@V$IEO(o*hQlD","inputs":{"VALUE":{"shadow":{"type":"text","id":"0(LMAx4.d%B)U5f1wVmS","fields":{"TEXT":""}},"block":{"type":"variables_get","id":"vSEU`a)R=Mm,Ce{bph`,","fields":{"VAR":{"id":"{.eDjfT}lMx@d$)CxF3/"}}}}}}},"DO0":{"block":{"type":"write_log","id":"mlhr!{j%p|%M~6$PDkF}","fields":{"FIELDVALUE1":"error"},"inputs":{"VALUE1":{"shadow":{"type":"text","id":"O{_L+{fZ}V|PGt8`[FRX","fields":{"TEXT":""}},"block":{"type":"text","id":"66G+-qYtpDm+jM8jb6E0","fields":{"TEXT":"Организация должна быть заполнена"}}}},"next":{"block":{"type":"call_raise","id":"g*Li}_Bu|iz,}9`ak.@6","inputs":{"VALUE":{"shadow":{"type":"text","id":"|0{ucCMQ*8.*bJm2I_k}","fields":{"TEXT":""}},"block":{"type":"text","id":"]-DWhM%hEI~.fBLa=ivg","fields":{"TEXT":"Организация должна быть заполнена"}}}}}}}}},"next":{"block":{"type":"controls_if","id":"+XnmZc$`?yrsD#uN,+L1","inputs":{"IF0":{"block":{"type":"logic_compare","id":"Jf+tXptS*:DV]TZI(MQH","fields":{"OP":"LTE"},"inputs":{"A":{"block":{"type":"variables_get","id":"Wp#hwBT6}mOJOJ[#-LXt","fields":{"VAR":{"id":"-s7qni$X]*-L9NA.r~gY"}}}},"B":{"block":{"type":"math_number","id":"v^a@x;8~b!S?yAI4NK.k","fields":{"NUM":0}}}}}},"DO0":{"block":{"type":"write_log","id":"%qmhliRgT[c!Cg]2jA*,","fields":{"FIELDVALUE1":"error"},"inputs":{"VALUE1":{"shadow":{"type":"text","id":"=G)Vg/p,WG,s[QXY08Ch","fields":{"TEXT":""}},"block":{"type":"text","id":"jD2;VMn{{@y9G%Su1t!e","fields":{"TEXT":"Сумма не должна равнятся нулю"}}}},"next":{"block":{"type":"call_raise","id":"QwKj4/UrXs1WFg5+xA]=","inputs":{"VALUE":{"shadow":{"type":"text","id":"E]`D]V1EK,Qfl`Puy+.}","fields":{"TEXT":""}},"block":{"type":"text","id":"cNkVXDWxSC94Z7cQzRq|","fields":{"TEXT":"Сумма не должна равнятся нулю"}}}}}}}}},"next":{"block":{"type":"controls_if","id":"t0ZEgI9ujaGXS3nXY(9Z","inputs":{"IF0":{"block":{"type":"logic_negate","id":"/6p=pK34F|N`E$+(E-]I","inputs":{"BOOL":{"block":{"type":"procedures_callreturn","id":"tB/N0Lk]8}Sk%f@G;1(3","extraState":{"name":"validate_by_regex","params":["value","pattern"]},"inputs":{"ARG0":{"block":{"type":"f_string","id":"$Qs50CMNak!}3Lzg2,%/","extraState":{},"fields":{"TEXT":"{inn}"}}},"ARG1":{"block":{"type":"text","id":"E4l[3OURUSiXrijgW}fY","fields":{"TEXT":"^\\d{10}(\\d{2})?$"}}}}}}}}},"DO0":{"block":{"type":"write_log","id":"u;9!L$7oDrlHV])#H9)=","fields":{"FIELDVALUE1":"error"},"inputs":{"VALUE1":{"shadow":{"type":"text","id":":|QxwxGALaOhGo;n33YR","fields":{"TEXT":""}},"block":{"type":"text","id":"OIt`e/0M$phuKNT3%Z}-","fields":{"TEXT":"ИНН некорректен"}}}},"next":{"block":{"type":"call_raise","id":"GOV_[.KmRbHn,=}!psFO","inputs":{"VALUE":{"shadow":{"type":"text","id":"Bh%`k^`?^2Htd9Od@Y+@","fields":{"TEXT":""}},"block":{"type":"text","id":"KFb9,O1nU3S8WcW,0q/q","fields":{"TEXT":"ИНН некорректен"}}}}}}}}}}}}}}}}}}}},"next":{"block":{"type":"write_log","id":"1OkFAB[J~-Ic~B=Ivs5/","fields":{"FIELDVALUE1":"info"},"inputs":{"VALUE1":{"shadow":{"type":"text","id":"c6I+M:hrWg]x`|)I?W{0","fields":{"TEXT":""}},"block":{"type":"f_string","id":"H-m$yyoQrjtdjA~DX%V=","extraState":{},"fields":{"TEXT":"Данные корректны"}}}}}}}}}}}}}}}},{"type":"procedures_defreturn","id":"!7`w`:-2]ITFu=HxBL(m","x":20,"y":2280,"extraState":{"procedureId":"KD3^{/ADRl/(12LJ@#tk"},"icons":{"comment":{"text":"Опишите эту функцию…","pinned":false,"height":80,"width":160}},"fields":{"NAME":"read_bank_statement"},"inputs":{"STACK":{"block":{"type":"comment_block","id":"ytmDEbvKG00|5NMs+:eA","fields":{"TEXT":"Выполняет чтение файла банковской выписки.\r\n\r\nФункция:\r\n- получает путь к файлу выписки из CONFIG;\r\n- проверяет существование файла;\r\n- определяет тип файла по расширению;\r\n- поддерживает чтение файлов:\r\n  - `.xlsx`\r\n  - `.csv`\r\n- считывает данные банковской выписки;\r\n- выполняет обработку ошибок чтения файла;\r\n- завершает выполнение программы при критических ошибках;\r\n- возвращает данные выписки `raw_statement`."},"next":{"block":{"type":"write_log","id":"E0zeLrKewV6(Gd=42;a.","fields":{"FIELDVALUE1":"info"},"inputs":{"VALUE1":{"shadow":{"type":"text","id":"/,2=yoH9SS3E.J%#hQ7r","fields":{"TEXT":""}},"block":{"type":"text","id":")0),+cb3^6^O!Yl}znGH","fields":{"TEXT":"Чтение файла банковской выписки..."}}}},"next":{"block":{"type":"group_block","id":":bE[8Ou._c^jwxZ:as^s","fields":{"FIELDVALUE":"Базовые пременные"},"inputs":{"DO":{"block":{"type":"variables_set","id":"RAe*,XYju~,-}/o(K9~p","fields":{"VAR":{"id":"irD!X.vYXFm/nrCsNxHU"}},"inputs":{"VALUE":{"block":{"type":"get_executable_path","id":"q]Mb$8EYT.+n+)jP-+1,","fields":{"FIELDVALUE1":true},"inputs":{"VALUE1":{"shadow":{"type":"text","id":"NZ+w][|OLe$|fHp-,qBE","fields":{"TEXT":""}},"block":{"type":"get_dict_value","id":"JQ{.acg@n_4Nu^UoPu#8","inputs":{"VALUE1":{"block":{"type":"use_constant","id":"QLw[IicK5sLXyvh=NT#j","fields":{"FIELDVALUE1":"CONFIG"}}},"VALUE2":{"shadow":{"type":"text","id":"qsbb*9i*fB}S.UUgs~9+","fields":{"TEXT":""}},"block":{"type":"text","id":"RLi%!dcg7K(]=t=s1RiY","fields":{"TEXT":"statement_file"}}}}}}}}}}}}},"next":{"block":{"type":"group_block","id":"=f*`JQ4.nafW.L*BtCdJ","fields":{"FIELDVALUE":"Входная проверка"},"inputs":{"DO":{"block":{"type":"controls_if","id":"[q*PKn5duH+xAL6BJ8h(","inputs":{"IF0":{"block":{"type":"logic_negate","id":"i@tN.$M8vznr~$BY,)w0","inputs":{"BOOL":{"block":{"type":"is_there_a_way_2","id":"F*7{To}Bh!PMUT1*7,6M","inputs":{"path_file":{"shadow":{"type":"text","id":",TuAZGRnx5/HeGp#T6`;","fields":{"TEXT":""}},"block":{"type":"variables_get","id":"eEla3m{Z38-a[Tmzi#lA","fields":{"VAR":{"id":"irD!X.vYXFm/nrCsNxHU"}}}}}}}}}},"DO0":{"block":{"type":"write_log","id":"*vQGpsKiBT2@zCq,x3EU","fields":{"FIELDVALUE1":"error"},"inputs":{"VALUE1":{"shadow":{"type":"text","id":"SjXTF)TAmef|uQ4[UZ0u","fields":{"TEXT":""}},"block":{"type":"text","id":"zqzZBuy%|pDru9=6y{sS","fields":{"TEXT":"Файл банковской выписки не найден"}}}},"next":{"block":{"type":"stop_robot","id":"HvhjV=[`j|lv~sF?csp^","inputs":{"VALUE1":{"shadow":{"type":"text","id":"hThr]/]#C@Z$eA}X*z!s","fields":{"TEXT":"Завершение работы робота"}}}}}}}}},"next":{"block":{"type":"write_log","id":"2=uVwrTT*O}D)aWzL4E5","fields":{"FIELDVALUE1":"info"},"inputs":{"VALUE1":{"shadow":{"type":"text","id":"W/EHZ,x(4^96.js;+E7l","fields":{"TEXT":""}},"block":{"type":"text","id":"[?2;vDBnBU!7WDB$?=j~","fields":{"TEXT":"Файл банковской выписки найден"}}}}}}}}},"next":{"block":{"type":"group_block","id":";=Xl|HQMLd-3+2U1uTfh","fields":{"FIELDVALUE":"Чтение файла"},"inputs":{"DO":{"block":{"type":"variables_set","id":"Ky8(ql4WgvHXdy;;+95#","fields":{"VAR":{"id":"8?~QZELuwqvvZPWbIqjE"}},"inputs":{"VALUE":{"block":{"type":"logic_boolean","id":"+J-5O$8M[)Ozki`q,3j0","fields":{"BOOL":"FALSE"}}}},"next":{"block":{"type":"variables_set","id":"111_^]4w5fWeuDRz,pR*","icons":{"comment":{"text":"Присваивает переменной значение вставки","pinned":false,"height":74,"width":211}},"fields":{"VAR":{"id":"H=r^kne);,^=u#UCvgNd"}},"inputs":{"VALUE":{"block":{"type":"get_file_metadata","id":"R+k%kZFsB2TVu=D7fx%_","fields":{"FIELDVALUE1":"file_extension"},"inputs":{"path_file":{"shadow":{"type":"text","id":"YhXB!dKZe-4^pl*rKyob","fields":{"TEXT":""}},"block":{"type":"variables_get","id":"EIiIPYL6~OF@),#J=*c5","fields":{"VAR":{"id":"irD!X.vYXFm/nrCsNxHU"}}}}}}}},"next":{"block":{"type":"try_except","id":"(-jt(H5+z`+P|W25C%@L","inputs":{"try":{"block":{"type":"controls_if","id":"yGXtommk~#U_#==9TM1x","inputs":{"IF0":{"block":{"type":"logic_compare","id":"4DU*Qlm7hPH{jGW*5Vj-","fields":{"OP":"EQ"},"inputs":{"A":{"block":{"type":"variables_get","id":"(lrSYw@5T4qAf@#UuStr","fields":{"VAR":{"id":"H=r^kne);,^=u#UCvgNd"}}}},"B":{"block":{"type":"text","id":"reC3dMdM/Lf$7{Kf_pV6","fields":{"TEXT":"xlsx"}}}}}},"DO0":{"block":{"type":"variables_set","id":"O:-NU+q49uvZ5k2b1YKo","icons":{"comment":{"text":"Присваивает переменной значение вставки","pinned":false,"height":74,"width":211}},"fields":{"VAR":{"id":"aS}c{;1cEiVjh7Y#/YkT"}},"inputs":{"VALUE":{"block":{"type":"excel_read_excel_new","id":"cucRp?8urr3VN$}GYX0M","fields":{"dictionaty_key_excel":"False"},"inputs":{"path_file":{"shadow":{"type":"text","id":"AC*ea]CgDZyN`4tf2XwS","fields":{"TEXT":""}},"block":{"type":"variables_get","id":"ucp,3fCwW?[.g|VHKj5a","fields":{"VAR":{"id":"irD!X.vYXFm/nrCsNxHU"}}}},"list":{"shadow":{"type":"text","id":"XC[:c%^)DWrw|1[FaCBR","fields":{"TEXT":""}},"block":{"type":"math_number","id":".aUpM/b=oM?g1,`wxkm.","fields":{"NUM":1}}},"column_dtypes":{"shadow":{"type":"logic_null","id":"@E^E^X(m$f@lLd@J1`Rq"}}}}}},"next":{"block":{"type":"variables_set","id":"5`ZZs3av/J;!I?f{r}uM","fields":{"VAR":{"id":"8?~QZELuwqvvZPWbIqjE"}},"inputs":{"VALUE":{"block":{"type":"logic_boolean","id":"***X-%:H/{X@8{{DtC}_","fields":{"BOOL":"TRUE"}}}}}}}}},"next":{"block":{"type":"controls_if","id":"MFs3dCG0zu}y/1_Ba[RD","inputs":{"IF0":{"block":{"type":"logic_compare","id":"P]@HH|@mV]6wjq(RT?%?","fields":{"OP":"EQ"},"inputs":{"A":{"block":{"type":"variables_get","id":"E^K[G+:di:/CFU*|aZUO","fields":{"VAR":{"id":"H=r^kne);,^=u#UCvgNd"}}}},"B":{"block":{"type":"text","id":"-OZaY4nol[YF:G`jzW4v","fields":{"TEXT":"csv"}}}}}},"DO0":{"block":{"type":"variables_set","id":"A_lcmKff2UZ}8U~YNVd;","icons":{"comment":{"text":"Присваивает переменной значение вставки","pinned":false,"height":74,"width":211}},"fields":{"VAR":{"id":"aS}c{;1cEiVjh7Y#/YkT"}},"inputs":{"VALUE":{"block":{"type":"read_file_3","id":"N3?6H8a1-DYp@O%CV6`)","extraState":"<mutation read_file_type=\"csv\"></mutation>","fields":{"fieldsCount":"csv","FIELDVALUE1":",","CSV_ENGINE":"pandas","CSV_HEADERS_MODE":"True"},"inputs":{"path":{"shadow":{"type":"text","id":"Ex/hcGVhPT%EKuD}z|bZ","fields":{"TEXT":""}},"block":{"type":"variables_get","id":"mDp/U]NnisXq8|H,YVf-","fields":{"VAR":{"id":"irD!X.vYXFm/nrCsNxHU"}}}},"encoding":{"shadow":{"type":"text","id":"k`R-!HWF9g%9pKj3YWs#","fields":{"TEXT":"utf-8"}}},"USECOLS":{"shadow":{"type":"logic_null","id":"UrhF(!iamX1H?E$nOgH4"}},"SKIPROWS":{"shadow":{"type":"logic_null","id":"V%+N)^v[/USL|2Dh%uB("}},"NROWS":{"shadow":{"type":"logic_null","id":"=~P;87Lo=G4trg=#-%/H"}},"COLUMN_DTYPES":{"shadow":{"type":"logic_null","id":"jZhpPEUVF|TcDN?o=$,t"}}}}}},"next":{"block":{"type":"variables_set","id":"~+lR*~91*$abu4+_/?eV","fields":{"VAR":{"id":"8?~QZELuwqvvZPWbIqjE"}},"inputs":{"VALUE":{"block":{"type":"logic_boolean","id":"LntSuK-)VF`)LrouA_=t","fields":{"BOOL":"TRUE"}}}}}}}}},"next":{"block":{"type":"controls_if","id":"w!6942$P,oyTY==dr8_Z","inputs":{"IF0":{"block":{"type":"logic_compare","id":"En|RL[xIOKNray/,fwox","fields":{"OP":"EQ"},"inputs":{"A":{"block":{"type":"variables_get","id":"^4I[^`5M8mNZf]H.4KA;","fields":{"VAR":{"id":"H=r^kne);,^=u#UCvgNd"}}}},"B":{"block":{"type":"text","id":"EDSF.}LLKnF~aRm$ro1H","fields":{"TEXT":"json"}}}}}},"DO0":{"block":{"type":"variables_set","id":"0ezx6[}2N|l-e.H.bdF8","icons":{"comment":{"text":"Присваивает переменной значение вставки","pinned":false,"height":74,"width":211}},"fields":{"VAR":{"id":"aS}c{;1cEiVjh7Y#/YkT"}},"inputs":{"VALUE":{"block":{"type":"read_file_3","id":";]5KG5h]+M-QzZB{x9{C","extraState":"<mutation read_file_type=\"json\"></mutation>","fields":{"fieldsCount":"json"},"inputs":{"path":{"shadow":{"type":"text","id":"XNdQGOCpO7(bL8Ks!HTr","fields":{"TEXT":""}},"block":{"type":"variables_get","id":"t[9d]oUtI:av^moIJf2h","fields":{"VAR":{"id":"irD!X.vYXFm/nrCsNxHU"}}}},"encoding":{"shadow":{"type":"text","id":"WV0?pnA{-7|7V$5me-]h","fields":{"TEXT":"utf-8"}}}}}}},"next":{"block":{"type":"variables_set","id":"f|o9%Zuq=Zd6~g^VD{w:","icons":{"comment":{"text":"Присваивает переменной значение вставки","pinned":false,"height":74,"width":211}},"fields":{"VAR":{"id":"aS}c{;1cEiVjh7Y#/YkT"}},"inputs":{"VALUE":{"block":{"type":"create_df","id":"*8.Ti~HC=WK%f%U?crvb","inputs":{"dict_value":{"block":{"type":"variables_get","id":"WDGt{#j_C^**A4C4@ZpQ","fields":{"VAR":{"id":"aS}c{;1cEiVjh7Y#/YkT"}}}}}}}},"next":{"block":{"type":"variables_set","id":"vMa4W2+@J4ze#ru,8(-R","fields":{"VAR":{"id":"8?~QZELuwqvvZPWbIqjE"}},"inputs":{"VALUE":{"block":{"type":"logic_boolean","id":"Of]N{MIj3D3oAqLJj*D^","fields":{"BOOL":"TRUE"}}}}}}}}}}},"next":{"block":{"type":"controls_if","id":"](f8_JdOsj!LJ6,D4z!w","inputs":{"IF0":{"block":{"type":"logic_negate","id":"lil(FXK:((|KOSdB0[L:","inputs":{"BOOL":{"block":{"type":"variables_get","id":"ok:XvNw%)4Ic{/4phor.","fields":{"VAR":{"id":"8?~QZELuwqvvZPWbIqjE"}}}}}}},"DO0":{"block":{"type":"write_log","id":"TLvk#6qsKKHSnuJ-3A?N","fields":{"FIELDVALUE1":"error"},"inputs":{"VALUE1":{"shadow":{"type":"text","id":"}0V-Z`4jxUbLg*9V%8ll","fields":{"TEXT":""}},"block":{"type":"text","id":"+Qf]0E17f7/@a.!]HGJN","fields":{"TEXT":"Ошибка чтения файла банковской выписки"}}}},"next":{"block":{"type":"stop_robot","id":"9w{D5?Gh)f`^~*?M@,w[","inputs":{"VALUE1":{"shadow":{"type":"text","id":"K]5Jj49^gtWQOsKC;NXz","fields":{"TEXT":"Завершение работы робота"}}}}}}}}}}}}}}}}},"except":{"block":{"type":"write_log","id":"5bm}T;GxgqqXD?p;9T0c","fields":{"FIELDVALUE1":"error"},"inputs":{"VALUE1":{"shadow":{"type":"text","id":")(Me[BQ@a_;whu}jJl55","fields":{"TEXT":""}},"block":{"type":"text","id":"ULrCSNoUlWi06tLBqN`Q","fields":{"TEXT":"Ошибка чтения файла банковской выписки"}}}},"next":{"block":{"type":"stop_robot","id":"94iI{-l]Ovz=?Cb2t!W1","inputs":{"VALUE1":{"shadow":{"type":"text","id":"RD($f9c_%DOMxKvj}Z@m","fields":{"TEXT":"Завершение работы робота"}}}}}}}},"error_description":{"block":{"type":"variables_get","id":"okk*=_8ZhRHCw?BBIzBW","fields":{"VAR":{"id":"K]^/?eL95JR*u}.NU7L("}}}}},"next":{"block":{"type":"write_log","id":"PQupbict[QQ;YMj{odaR","fields":{"FIELDVALUE1":"info"},"inputs":{"VALUE1":{"shadow":{"type":"text","id":"_|{0gTj_{[LLd$da{bZV","fields":{"TEXT":""}},"block":{"type":"text","id":"RF)8~AZx3bY+88%Eqchh","fields":{"TEXT":"Чтение банковской выписки успешно"}}}}}}}}}}}}},"next":{"block":{"type":"group_block","id":"l,#5.rN!d1N2x+C.aE3+","fields":{"FIELDVALUE":"Валидация данных"},"inputs":{"DO":{"block":{"type":"procedures_callnoreturn","id":"-aTGo1OJ)_Ih7Av!%m[6","extraState":{"name":"validate_bank_statement","params":["statement"]},"inputs":{"ARG0":{"block":{"type":"variables_get","id":"`]7bhlWpp|WHe@QUOnSj","fields":{"VAR":{"id":"aS}c{;1cEiVjh7Y#/YkT"}}}}}}}},"next":{"block":{"type":"write_log","id":"JRgIKyD35K^:}cO%[z1p","fields":{"FIELDVALUE1":"info"},"inputs":{"VALUE1":{"shadow":{"type":"text","id":"A^Vy{.T$*q*,plY@#!Mt","fields":{"TEXT":""}},"block":{"type":"text","id":"GyAKbb#hnJjfgriCK1t*","fields":{"TEXT":"Банковская выписка готова к работе"}}}}}}}}}}}}}}}}}},"RETURN":{"block":{"type":"variables_get","id":"ZZMZS1-*t?D!aTd{vv(N","fields":{"VAR":{"id":"aS}c{;1cEiVjh7Y#/YkT"}}}}}}]},"variables":[{"name":"value","id":"p`a-ZY/1_BAC}wTk*]%1","global":false},{"name":"pattern","id":"m;F[q_2tveGoFelpKGjz","global":false},{"name":"config_path","id":"o(4KrG#~FOUyEUw|({w2","global":false},{"name":"config","id":"=cnGp7w^(zc|[v+6$0!/","global":false},{"name":"statement","id":"%9v@:^Vx-]2?^Zi%Tcv}","global":false},{"name":"row","id":"_/vg4^P)]TBw7}27jSv^","global":false},{"name":"payment","id":"d5f^:-h;moNE(c|j!a,2","global":false},{"name":"total_count","id":"2rZUQ%weKke.FYdg~}(*","global":false},{"name":"success_count","id":"N.q!}r#YUwK.j7(e2m_y","global":false},{"name":"error_count","id":"?Uh[i#l8W$2zs[HXGe^U","global":false},{"name":"duplicate_count","id":"6nDmXZu$Nj_?)P[}F+Lf","global":false},{"name":"skipped_count","id":"s{ILW{ydH!mUH!BiBa*q","global":false},{"name":"results","id":"f[hwD?_=SHxkc]Zm^rjC","global":false},{"name":"document_ref","id":"$V8eK:GAwlczn~4LCty5","global":false},{"name":"status","id":"19Q.ax@f[XGIaT=,t3z4","global":false},{"name":"message","id":"`BK[nI-yfFhd[3],D:yF","global":false},{"name":"document_type","id":".Kwkhl$,J3fe(?Z_w}b{","global":false},{"name":"statement_path","id":"irD!X.vYXFm/nrCsNxHU","global":false},{"name":"raw_statement","id":"aS}c{;1cEiVjh7Y#/YkT","global":false},{"name":"statement_file_type","id":"H=r^kne);,^=u#UCvgNd","global":false},{"name":"error_description","id":"K]^/?eL95JR*u}.NU7L(","global":false},{"name":"is_read","id":"8?~QZELuwqvvZPWbIqjE","global":false},{"name":"date","id":"Ak[:Ef9D~ZyYr3^brKGD","global":false},{"name":"amount","id":"-s7qni$X]*-L9NA.r~gY","global":false},{"name":"inn","id":"RR,qkAXttU(`7i8db=4|","global":false},{"name":"organization","id":"{.eDjfT}lMx@d$)CxF3/","global":false},{"name":"purpose","id":"GQuOgS:OP^}_`hVF88Se","global":false},{"name":"raw_type","id":"w8WPv#Ht@]Jf08+Ym|3W","global":false},{"name":"required_columns","id":"(W.XicDr)K8pasW5op.y","global":false},{"name":"column","id":"MKoy}V;0qs@|B2tb1[4L","global":false},{"name":"columns","id":"%fM.Cf@lHUEcY$B#9+JD","global":false},{"name":"count","id":"+MiW%nzLA[a{Y`?W2#A5","global":false}],"procedures":[{"id":"45UsdLdvQJUcTj~oJ)AF","name":"load_config","returnTypes":[]},{"id":"6W[(hB4r1bY?S8KH@EWt","name":"validate_by_regex","returnTypes":[],"parameters":[{"id":"G$:FBZ~]2]LA(7t$|YBd","name":"value"},{"id":"nc$8#n9DcZ1E)9cx69M~","name":"pattern"}]},{"id":"hn|L/^+|x)#saX3G|5i9","name":"read_config","returnTypes":[],"parameters":[{"id":"G2`E,@.IC@,t2#*h6*^Q","name":"config_path"}]},{"id":"9v2,0Zt|FdK;vtYjXeQ3","name":"prepare_config","returnTypes":[],"parameters":[{"id":".7flw)J~]3%/{et/`ZhT","name":"config"}]},{"id":"KD3^{/ADRl/(12LJ@#tk","name":"read_bank_statement","returnTypes":[]},{"id":"Ih5!k9+Fw?I6be,p}+@$","name":"validate_bank_statement","returnTypes":null,"parameters":[{"id":"hx-5v#m`45Dpqs`3ovV*","name":"statement"}]},{"id":"v?m+zr|}6[5e6`.}tvpe","name":"validate_payment_row","returnTypes":null,"parameters":[{"id":"oI2MQVRsCOkByXErb[C7","name":"row"}]},{"id":"nEJ/S!1pz7W[Y;%;F(g4","name":"define_operation_type","returnTypes":[],"parameters":[{"id":"{1/|[0[$0y{N4/[bEU*T","name":"payment"}]},{"id":"pl+I}h]=.A=#{FV=V|/B","name":"finalize_processing","returnTypes":null,"parameters":[{"id":"2h+/3@WdSkT]RyT63c1C","name":"total_count"},{"id":"?nlUoSG#]UPA*S(ci?Kf","name":"success_count"},{"id":"p.rr`iAn*^bxf|A@XXf`","name":"error_count"},{"id":"6C9}WD.U)m=aF:@R0%8Y","name":"duplicate_count"}]},{"id":"SNLHSK}5M%oWt0[i;~6u","name":"process_statement_rows","returnTypes":null,"parameters":[{"id":"ZH^_N_2GiEqjSBFfuLEG","name":"statement"}]},{"id":"z%;g~7T%[k4mY5frPlf5","name":"save_report","returnTypes":null,"parameters":[{"id":"CdQmhwQbv%3=mSH6:A/6","name":"results"}]},{"id":"7cmH|u=H@uqLgf|(kV.Q","name":"add_result","returnTypes":null,"parameters":[{"id":"vp$OUw~l3iAiJA3OD`P.","name":"results"},{"id":"xdkZ5EFK[u,|_k};cPVT","name":"payment"},{"id":"5z%LwqEaLG1dR6sz(yy}","name":"status"},{"id":"nCBj-?L:m;y2f6!DpP?N","name":"message"},{"id":"+hTbj)|$_8qi`q!i::$p","name":"document_ref"}]},{"id":"1JQ4F#F!OU+fRY3Q@N(;","name":"open_1c_web","returnTypes":[]},{"id":"K~J/AscGhGenhzsdG7Zx","name":"login_1c_web","returnTypes":null},{"id":"^;SAvoJ:k%LB^@VWS7o_","name":"open_bank_statements_table_web","returnTypes":null},{"id":"oc*12J.{|JZ?CM85O~hK","name":"create_1c_document","returnTypes":null,"parameters":[{"id":"6qEMbyO+e7g:gH$lh.^x","name":"payment"},{"id":"GZ(Z}`0Cl8LpJCNO.Gp2","name":"document_type"},{"id":".Ej(j09k*nD81mC@Rx~N","name":"count"}]},{"id":"[o$[CZS6{8W`Atp}5Sv0","name":"get_document_link_1c","returnTypes":[],"parameters":[{"id":"JrX(w/8?pf8i)@%9g7v|","name":"payment"}]},{"id":"=o}Cttb{=C#@Y5{V,+Ap","name":"find_document_1c","returnTypes":[],"parameters":[{"id":"3+$8{)BnQYr1#^_qq*L2","name":"payment"}]},{"id":"d_W1Rn]$_Sh$l7HtNH7x","name":"check_duplicate","returnTypes":[],"parameters":[{"id":"9|+X|b7Ee?1uK/{^,3x}","name":"payment"}]}]},"dataStorage":{"webUiStorage":{}}},"workspaceMeta":{"undoStack":[],"redoStack":[],"x":106.0466809127247,"y":-4380.1685329619795,"trashcan":[],"scale":1.2899450879999999},"pId":"synth_656"}
